antchain_sdk_ak_1470b9714f184f1885db246eb9933e95/__init__.py
antchain_sdk_ak_1470b9714f184f1885db246eb9933e95/client.py
antchain_sdk_ak_1470b9714f184f1885db246eb9933e95/models.py
antchain_ak_1470b9714f184f1885db246eb9933e95-1.0.5.dist-info/LICENSE
antchain_ak_1470b9714f184f1885db246eb9933e95-1.0.5.dist-info/METADATA
antchain_ak_1470b9714f184f1885db246eb9933e95-1.0.5.dist-info/WHEEL
antchain_ak_1470b9714f184f1885db246eb9933e95-1.0.5.dist-info/top_level.txt
antchain_ak_1470b9714f184f1885db246eb9933e95-1.0.5.dist-info/RECORD
